harlequin_clickhouse/__init__.py
harlequin_clickhouse/adapter.py
harlequin_clickhouse/cli_options.py
harlequin_clickhouse/py.typed
harlequin_clickhouse-0.1.1.dist-info/WHEEL
harlequin_clickhouse-0.1.1.dist-info/entry_points.txt
harlequin_clickhouse-0.1.1.dist-info/METADATA
harlequin_clickhouse-0.1.1.dist-info/RECORD
