Metadata-Version: 2.3
Name: harlequin-clickhouse
Version: 0.1.1
Summary: A Harlequin adapter for Clickhouse
Keywords: harlequin,clickhouse,sql,tui
Author: Thomaub
Author-email: Thomaub <github.thomaub@gmail.com>
License: MIT
Classifier: Development Status :: 4 - Beta
Classifier: Environment :: Console
Classifier: Intended Audience :: Developers
Classifier: License :: OSI Approved :: MIT License
Classifier: Operating System :: OS Independent
Classifier: Programming Language :: Python :: 3
Classifier: Programming Language :: Python :: 3.9
Classifier: Programming Language :: Python :: 3.10
Classifier: Programming Language :: Python :: 3.11
Classifier: Programming Language :: Python :: 3.12
Classifier: Programming Language :: Python :: 3.13
Classifier: Topic :: Database
Classifier: Typing :: Typed
Requires-Dist: harlequin>=2.0
Requires-Dist: clickhouse-driver>=0.2.7
Requires-Dist: ruff>=0.1.6 ; extra == 'dev'
Requires-Dist: pytest>=7.4.3 ; extra == 'dev'
Requires-Dist: mypy>=1.7.0 ; extra == 'dev'
Requires-Dist: pre-commit>=3.5.0 ; extra == 'dev'
Requires-Dist: importlib-metadata>=4.6.0 ; python_full_version < '3.10' and extra == 'dev'
Requires-Dist: testcontainers[clickhouse]>=4.4.0 ; extra == 'dev'
Requires-Python: >=3.9, <3.14.0
Project-URL: Homepage, https://github.com/harlequin-org/harlequin-clickhouse
Project-URL: Issues, https://github.com/harlequin-org/harlequin-clickhouse/issues
Project-URL: Repository, https://github.com/harlequin-org/harlequin-clickhouse
Provides-Extra: dev
